CONTRIBUTING.md
LICENSE
MANIFEST.in
README.md
THIRD_PARTY_LIC
setup.py
boards/Pynq-Z1/base/__init__.py
boards/Pynq-Z1/base/base.bit
boards/Pynq-Z1/base/base.hwh
boards/Pynq-Z1/base/base.py
boards/Pynq-Z1/base/base.tcl
boards/Pynq-Z1/base/build_bitstream.tcl
boards/Pynq-Z1/base/build_ip.tcl
boards/Pynq-Z1/base/check_timing.tcl
boards/Pynq-Z1/base/constants.py
boards/Pynq-Z1/base/notebooks/arduino/arduino_analog.ipynb
boards/Pynq-Z1/base/notebooks/arduino/arduino_ardumoto.ipynb
boards/Pynq-Z1/base/notebooks/arduino/arduino_grove_gesture.ipynb
boards/Pynq-Z1/base/notebooks/arduino/arduino_grove_ledbar.ipynb
boards/Pynq-Z1/base/notebooks/arduino/arduino_joystick.ipynb
boards/Pynq-Z1/base/notebooks/arduino/arduino_lcd18.ipynb
boards/Pynq-Z1/base/notebooks/arduino/data/adafruit_lcd18.jpg
boards/Pynq-Z1/base/notebooks/arduino/data/ardumoto_wiring.jpg
boards/Pynq-Z1/base/notebooks/arduino/data/board_small.jpg
boards/Pynq-Z1/base/notebooks/arduino/data/logo_small.png
boards/Pynq-Z1/base/notebooks/audio/audio_playback.ipynb
boards/Pynq-Z1/base/notebooks/board/asyncio_buttons.ipynb
boards/Pynq-Z1/base/notebooks/board/board_btns_leds.ipynb
boards/Pynq-Z1/base/notebooks/board/register_map_intro.ipynb
boards/Pynq-Z1/base/notebooks/microblaze/microblaze_c_libraries.ipynb
boards/Pynq-Z1/base/notebooks/microblaze/microblaze_programming.ipynb
boards/Pynq-Z1/base/notebooks/microblaze/microblaze_python_libraries.ipynb
boards/Pynq-Z1/base/notebooks/pmod/pmod_adc.ipynb
boards/Pynq-Z1/base/notebooks/pmod/pmod_als.ipynb
boards/Pynq-Z1/base/notebooks/pmod/pmod_dac_adc.ipynb
boards/Pynq-Z1/base/notebooks/pmod/pmod_grove_adc.ipynb
boards/Pynq-Z1/base/notebooks/pmod/pmod_grove_buzzer.ipynb
boards/Pynq-Z1/base/notebooks/pmod/pmod_grove_light.ipynb
boards/Pynq-Z1/base/notebooks/pmod/pmod_grove_oled.ipynb
boards/Pynq-Z1/base/notebooks/pmod/pmod_grove_pir.ipynb
boards/Pynq-Z1/base/notebooks/pmod/pmod_grove_tmp.ipynb
boards/Pynq-Z1/base/notebooks/pmod/pmod_grove_usranger.ipynb
pynq.egg-info/PKG-INFO
pynq.egg-info/SOURCES.txt
pynq.egg-info/dependency_links.txt
pynq.egg-info/entry_points.txt
pynq.egg-info/not-zip-safe
pynq.egg-info/requires.txt
pynq.egg-info/top_level.txt
