Metadata-Version: 2.1
Name: pynq
Version: 3.1.2
Summary: (PY)thon productivity for zy(NQ)
Home-page: https://github.com/Xilinx/PYNQ
Download-URL: https://github.com/Xilinx/PYNQ
Author: Xilinx PYNQ Development Team
Author-email: pynq_support@xilinx.com
License: BSD 3-Clause
Requires-Python: >=3.5.2
License-File: LICENSE
